cinnamon/__init__.py
cinnamon/common/__init__.py
cinnamon/common/constants.py
cinnamon/common/dev_utils.py
cinnamon/common/logging.py
cinnamon/common/math_utils.py
cinnamon/common/stat_utils.py
cinnamon/drift/__init__.py
cinnamon/drift/abstract_drift_explainer.py
cinnamon/drift/adversarial_drift_explainer.py
cinnamon/drift/drift_utils.py
cinnamon/drift/model_drift_explainer.py
cinnamon/drift/output_drift_detector.py
cinnamon/drift/tree_ensemble_drift_explainer.py
cinnamon/drift/tests/__init__.py
cinnamon/drift/tests/test_LinearRegression_ModelDriftExplainer.py
cinnamon/drift/tests/test_LogisticRegression_ModelDriftExplainer.py
cinnamon/drift/tests/test_adversarial_drift_explainer.py
cinnamon/drift/tests/test_catboost_model_drift_explainer.py
cinnamon/drift/tests/test_output_drift_detector.py
cinnamon/drift/tests/test_xgboost_model_drift_explainer.py
cinnamon/model_parser/__init__.py
cinnamon/model_parser/abstract_model_parser.py
cinnamon/model_parser/abstract_tree_ensemble_parser.py
cinnamon/model_parser/catboost_parser.py
cinnamon/model_parser/model_agnostic_model_parser.py
cinnamon/model_parser/single_tree.py
cinnamon/model_parser/xgboost_parser.py
cinnamon/plot/__init__.py
cinnamon/plot/drift/__init__.py
cinnamon/plot/drift/plot_drift.py
cinnamon/plot/drift/plot_drift_importance.py
cinnamon/plot/drift/plot_tree_drift.py
cinnamon/plot/drift/plot_utils.py
cinnamon/report/__init__.py
cinnamon/report/drift_report_generator.py
cinnamon/report/i_report_generator.py
cinnamon-0.2.1.dist-info/LICENSE.txt
cinnamon-0.2.1.dist-info/METADATA
cinnamon-0.2.1.dist-info/WHEEL
cinnamon-0.2.1.dist-info/top_level.txt
cinnamon-0.2.1.dist-info/RECORD
