Metadata-Version: 2.1
Name: cinnamon
Version: 0.2.1
Summary: A monitoring tool for machine learning systems that focus on data drift
Home-page: https://github.com/zelros/cinnamon
Author: Yohann Le Faou
Author-email: lefaou.yohann@gmail.com
License: MIT
Project-URL: Source Code, https://github.com/zelros/cinnamon
Project-URL: Bug Tracker, https://github.com/zelros/cinnamon/issues
Keywords: data drift,covariate shift,concept drift,monitoring,adversarial learning,machine learning
Classifier: Intended Audience :: Science/Research
Classifier: Intended Audience :: Developers
Classifier: Topic :: Software Development
Classifier: Topic :: Scientific/Engineering
Classifier: Programming Language :: Python :: 3
Classifier: License :: OSI Approved :: MIT License
Classifier: Operating System :: OS Independent
Requires-Python: >=3.7
License-File: LICENSE.txt
Requires-Dist: pandas (>=1.0)
Requires-Dist: scikit-learn (>=1.0)
Requires-Dist: xgboost (>=1.4)
Requires-Dist: catboost (>=1.0)
Provides-Extra: graphs
Requires-Dist: matplotlib (>=3.4.3) ; extra == 'graphs'
Requires-Dist: treelib (>=1.6.1) ; extra == 'graphs'
